proto/zhiyan_rpc_pb2.py
proto/zhiyan_rpc_pb2_grpc.py
zygrpc_help/__init__.py
zygrpc_help/version.txt
zygrpc-0.0.1.15.dist-info/LICENSE
zygrpc-0.0.1.15.dist-info/METADATA
zygrpc-0.0.1.15.dist-info/WHEEL
zygrpc-0.0.1.15.dist-info/top_level.txt
zygrpc-0.0.1.15.dist-info/RECORD
