Metadata-Version: 2.1
Name: zygrpc
Version: 0.0.1.15
Summary: ZhiYan Python gRPC SDK
Author-email: Chengdu Geek Camp <lq@cdgeekcamp.com>
License: MIT
Project-URL: Documentation, https://gitee.com/warp-drive-tech/libzygrpc
Project-URL: Source, https://gitee.com/warp-drive-tech/libzygrpc
Project-URL: Home-page, https://gitee.com/warp-drive-tech/libzygrpc
Classifier: Operating System :: POSIX :: Linux
Classifier: Intended Audience :: Developers
Classifier: License :: OSI Approved :: MIT License
Classifier: Operating System :: OS Independent
Classifier: Programming Language :: Python
Classifier: Programming Language :: Python :: 3
Classifier: Topic :: Software Development :: Libraries :: Python Modules
Requires-Python: >=3.8.5
License-File: LICENSE
Requires-Dist: grpcio-tools
Requires-Dist: grpcio
Requires-Dist: protobuf
